pysem_converters/__init__.py
pysem_converters/distance.py
pysem_converters/objects.py
pysem_converters/temperature.py
pysem_converters/time.py
pysem_converters-0.2.dist-info/LICENSE
pysem_converters-0.2.dist-info/METADATA
pysem_converters-0.2.dist-info/WHEEL
pysem_converters-0.2.dist-info/top_level.txt
pysem_converters-0.2.dist-info/RECORD
