Metadata-Version: 2.1
Name: pysem-converters
Version: 0.2
Summary: UNKNOWN
Home-page: https://github.com/pysem/converters
Author: Adrián Toral
Author-email: adriantoral@sertor.es
License: UNKNOWN
Project-URL: Website, https://github.com/pysem/converters
Project-URL: Issues, https://github.com/pysem/converters/issues
Keywords: python,converters,utilities,python-converters,python-converters-utilities
Platform: UNKNOWN
Classifier: Programming Language :: Python :: 3
Classifier: License :: OSI Approved :: GNU General Public License v3 (GPLv3)
Classifier: Operating System :: OS Independent
Classifier: Topic :: Software Development :: Libraries :: Python Modules
Requires-Python: >=3.8
License-File: LICENSE
